libllama-embedder.dylib
llama_embedder.cpython-39-darwin.so
llama_embedder-0.0.7.dist-info/LICENSE.md
llama_embedder-0.0.7.dist-info/RECORD
llama_embedder-0.0.7.dist-info/WHEEL
llama_embedder-0.0.7.dist-info/top_level.txt
llama_embedder-0.0.7.dist-info/METADATA
bindings/python/llama_embedder/__init__.py
