Metadata-Version: 2.1
Name: llama_embedder
Version: 0.0.7
Summary: LLama.cpp embedder library python bindings
Author-email: Trayan Azarov <trayan.azarov@amikos.tech>
License: The MIT License
Classifier: Development Status :: 3 - Alpha
Classifier: Intended Audience :: Developers
Classifier: License :: OSI Approved :: MIT License
Classifier: Programming Language :: Python :: 3
Classifier: Programming Language :: Python :: 3.8
Classifier: Programming Language :: Python :: 3.9
Classifier: Programming Language :: Python :: 3.10
Classifier: Programming Language :: Python :: 3.11
Classifier: Programming Language :: Python :: 3.12
Requires-Python: >=3.8
License-File: LICENSE.md
Provides-Extra: test
Requires-Dist: pytest>=6.0; extra == "test"
